{
"type": "FeatureCollection",
"crs": { "type": "name", "properties": { "name": "urn:ogc:def:crs:OGC:1.3:CRS84" } },
                                                                                
"features": [
{ "type": "Feature", "properties": { "dot_un_id_": "UN3077", "dot_un_i_1": "Environmentally hazardous substances, solid, n.o.s.", "dot_packin": "III", "total_quan": 24.0, "units_for_": "P - Pounds", "receivin_2": "CLEAN HARBORS INC", "receivin_3": "2027 BATTLEGROUND ROAD", "receivin_4": "LA PORTE", "receivin_5": "TX", "receivin_6": 77571, "Vol-I": 0.0, "Vol-II": null, "Vol-III": null, "Vol-U": 0.0, "Mass-I": 0.0, "Mass-II": 13619.0, "Mass-III": 6562.0, "Mass-U": 0.0 }, "geometry": { "type": "Point", "coordinates": [ -82.071438, 41.379149 ] } },
{ "type": "Feature", "properties": { "dot_un_id_": "UN3249", "dot_un_i_1": "Medicine, solid, toxic, n.o.s.", "dot_packin": null, "total_quan": 85.0, "units_for_": "K - Kilograms", "receivin_2": "ROSS INCINERATION SERVICES INC", "receivin_3": "36790 GILES ROAD", "receivin_4": "GRAFTON", "receivin_5": "OH", "receivin_6": 44044, "Vol-I": 0.0, "Vol-II": 0.0, "Vol-III": 0.0, "Vol-U": 0.0, "Mass-I": 0.0, "Mass-II": 461305.05, "Mass-III": 0.0, "Mass-U": 116397.32 }, "geometry": { "type": "Point", "coordinates": [ -82.048136783199993, 41.326674751600002 ] } },
{ "type": "Feature", "properties": { "dot_un_id_": "UN1805", "dot_un_i_1": "Phosphoric acid solution", "dot_packin": "III", "total_quan": 352.0, "units_for_": "P - Pounds", "receivin_2": "CLEAN HARBORS INC", "receivin_3": "2900 ROCKEFELLER AVENUE", "receivin_4": "CLEVELAND", "receivin_5": "OH", "receivin_6": 44115, "Vol-I": 0.0, "Vol-II": 0.0, "Vol-III": 0.0, "Vol-U": 0.0, "Mass-I": 0.0, "Mass-II": 40389.0, "Mass-III": 1997.0, "Mass-U": 0.0 }, "geometry": { "type": "Point", "coordinates": [ -81.668384, 41.480750188800002 ] } },
{ "type": "Feature", "properties": { "dot_un_id_": "UN3264", "dot_un_i_1": "Corrosive liquid, acidic, inorganic, n.o.s.", "dot_packin": "II", "total_quan": 1796.0, "units_for_": "G - Gallons", "receivin_2": "ENVIRITE OF OHIO", "receivin_3": "2050 CENTRAL AVE", "receivin_4": "CANTON", "receivin_5": "OH", "receivin_6": 44707, "Vol-I": 0.0, "Vol-II": 761811.06, "Vol-III": 5542.0, "Vol-U": 0.0, "Mass-I": 0.0, "Mass-II": 0.0, "Mass-III": 755711.0, "Mass-U": 0.0 }, "geometry": { "type": "Point", "coordinates": [ -81.369830901399993, 40.7753751268 ] } },
{ "type": "Feature", "properties": { "dot_un_id_": "UN1992", "dot_un_i_1": "Flammable liquids, toxic, n.o.s.", "dot_packin": "II", "total_quan": 18360.0, "units_for_": "L - Liters", "receivin_2": "HERITAGE-WTI INC", "receivin_3": "1250 ST GEORGE ST", "receivin_4": "EAST LIVERPOOL", "receivin_5": "OH", "receivin_6": 43920, "Vol-I": 0.0, "Vol-II": 99087.48, "Vol-III": 0.0, "Vol-U": 0.0, "Mass-I": 0.0, "Mass-II": 0.0, "Mass-III": 413313.83, "Mass-U": 0.0 }, "geometry": { "type": "Point", "coordinates": [ -80.548620510199996, 40.6313754082 ] } },
{ "type": "Feature", "properties": { "dot_un_id_": null, "dot_un_i_1": null, "dot_packin": null, "total_quan": 55.0, "units_for_": "G - Gallons", "receivin_2": "SPRING GROVE RESOURCE RECOVERY INC", "receivin_3": "4879 SPRING GROVE AVENUE", "receivin_4": "CINCINNATI", "receivin_5": "OH", "receivin_6": 45232, "Vol-I": 0.0, "Vol-II": 28213.51, "Vol-III": 2112.52, "Vol-U": 631.99, "Mass-I": 0.0, "Mass-II": 242768.35, "Mass-III": 11287.65, "Mass-U": 0.0 }, "geometry": { "type": "Point", "coordinates": [ -84.513717, 39.16646 ] } },
{ "type": "Feature", "properties": { "dot_un_id_": "UN1992", "dot_un_i_1": "Flammable liquids, toxic, n.o.s.", "dot_packin": "II", "total_quan": 45388.0, "units_for_": "P - Pounds", "receivin_2": "SYSTECH ENVIRONMENTAL", "receivin_3": "11397 CO RD 176", "receivin_4": "PAULDING", "receivin_5": "OH", "receivin_6": 45879, "Vol-I": 0.0, "Vol-II": 86910.0, "Vol-III": 0.0, "Vol-U": 5000.0, "Mass-I": 0.0, "Mass-II": 126070.0, "Mass-III": 0.0, "Mass-U": 0.0 }, "geometry": { "type": "Point", "coordinates": [ -84.532406, 41.121205 ] } }
]
}
